anshin/__init__.py
anshin/example.py
anshin-0.1a2.dev1.dist-info/METADATA
anshin-0.1a2.dev1.dist-info/WHEEL
anshin-0.1a2.dev1.dist-info/licenses/LICENSE-APACHE
anshin-0.1a2.dev1.dist-info/licenses/LICENSE-GPLv3
anshin-0.1a2.dev1.dist-info/RECORD
