Metadata-Version: 2.4
Name: anshin
Version: 0.1a2.dev1
Summary: anshin is a Python/TOML-based system build tool.
Project-URL: Homepage, https://gitlab.com/anshin-dev-group/anshin
Project-URL: Issues, https://gitlab.com/anshin-dev-group/anshin/issues
Author: anshin-dev
Maintainer: anshin-dev
License-Expression: Apache-2.0 OR GPL-3.0-or-later
License-File: LICENSE-APACHE
License-File: LICENSE-GPLv3
Keywords: build,configuration,reproducible,system
Classifier: Development Status :: 2 - Pre-Alpha
Classifier: Programming Language :: Python :: 3
Classifier: Programming Language :: Python :: 3 :: Only
Requires-Python: >=3.14
